{
  "Routes": [
    {
      "UpstreamPathTemplate": "/api/clients/{everything}",
      "UpstreamHttpMethod": [ "GET", "POST", "PUT", "PATCH", "DELETE" ],
      "DownstreamPathTemplate": "/api/clients/{everything}",
      "DownstreamScheme": "http",
      "DownstreamHostAndPorts": [ { "Host": "localhost", "Port": 5263 } ],
      "RateLimitOptions": {
        "EnableRateLimiting": true,
        "Period": "1s",
        "PeriodTimespan": 1,
        "Limit": 20
      }
    },
    {
      "UpstreamPathTemplate": "/api/Advertisements/{everything}",
      "UpstreamHttpMethod": [ "GET", "POST", "PUT", "PATCH", "DELETE" ],
      "DownstreamPathTemplate": "/api/Advertisements/{everything}",
      "DownstreamScheme": "http",
      "DownstreamHostAndPorts": [ { "Host": "localhost", "Port": 5104 } ],
      "RateLimitOptions": {
        "EnableRateLimiting": true,
        "Period": "1s",
        "PeriodTimespan": 1,
        "Limit": 20
      }
    },
    {
      "UpstreamPathTemplate": "/api/Companies/{everything}",
      "UpstreamHttpMethod": [ "GET", "POST", "PUT", "PATCH", "DELETE" ],
      "DownstreamPathTemplate": "/api/Companies/{everything}",
      "DownstreamScheme": "http",
      "DownstreamHostAndPorts": [ { "Host": "localhost", "Port": 5287 } ],
      "RateLimitOptions": {
        "EnableRateLimiting": true,
        "Period": "1s",
        "PeriodTimespan": 1,
        "Limit": 20
      }
    },
    {
      "UpstreamPathTemplate": "/api/notifications/{everything}",
      "UpstreamHttpMethod": [ "GET", "POST", "PUT", "PATCH", "DELETE" ],
      "DownstreamPathTemplate": "/api/notifications/{everything}",
      "DownstreamScheme": "http",
      "DownstreamHostAndPorts": [ { "Host": "localhost", "Port": 5199 } ],
      "RateLimitOptions": {
        "EnableRateLimiting": true,
        "Period": "1s",
        "PeriodTimespan": 1,
        "Limit": 20
      }
    },
    {
      "UpstreamPathTemplate": "/api/job-applications/{everything}",
      "UpstreamHttpMethod": [ "GET", "POST", "PUT", "PATCH", "DELETE" ],
      "DownstreamPathTemplate": "/api/job-applications/{everything}",
      "DownstreamScheme": "http",
      "DownstreamHostAndPorts": [ { "Host": "localhost", "Port": 5291 } ],
      "RateLimitOptions": {
        "EnableRateLimiting": true,
        "Period": "1s",
        "PeriodTimespan": 1,
        "Limit": 20
      }
    },
    {
      "UpstreamPathTemplate": "/api/Auth/{everything}",
      "UpstreamHttpMethod": [ "GET", "POST", "PUT", "PATCH", "DELETE" ],
      "DownstreamPathTemplate": "/api/Auth/{everything}",
      "DownstreamScheme": "http",
      "DownstreamHostAndPorts": [ { "Host": "localhost", "Port": 5218 } ],
      "RateLimitOptions": {
        "EnableRateLimiting": true,
        "Period": "1s",
        "PeriodTimespan": 1,
        "Limit": 20
      }
    },
    {
      "UpstreamPathTemplate": "/api/{everything}",
      "UpstreamHttpMethod": [ "GET", "POST", "PUT", "PATCH", "DELETE" ],
      "DownstreamPathTemplate": "/api/{everything}",
      "DownstreamScheme": "http",
      "DownstreamHostAndPorts": [ { "Host": "localhost", "Port": 5218 } ],
      "RateLimitOptions": {
        "EnableRateLimiting": true,
        "Period": "1s",
        "PeriodTimespan": 1,
        "Limit": 20
      }
    }
  ],
  "GlobalConfiguration": {
    "BaseUrl": "http://localhost:5000",
    "RateLimitOptions": {
      "ClientIdHeader": "ClientId",
      "QuotaExceededMessage": "Previse zahteva, pokusajte ponovo kasnije.",
      "RateLimitCounterPrefix": "jobless-gw",
      "DisableRateLimitHeaders": false,
      "HttpStatusCode": 429
    }
  }
}
